oigrader/__init__.py
oigrader/oigrader.py
oigrader-0.1.2.dist-info/LICENSE
oigrader-0.1.2.dist-info/METADATA
oigrader-0.1.2.dist-info/WHEEL
oigrader-0.1.2.dist-info/top_level.txt
oigrader-0.1.2.dist-info/RECORD
