Metadata-Version: 2.1
Name: oigrader
Version: 0.1.2
Summary: Module to grade online quiz.
Home-page: https://github.com/yiyitech/grademage
Author: Samuel Zhang
Author-email: qisamuelzhang@hotmail.com
License: MIT
License-File: LICENSE
Requires-Dist: requests
